abacusevents/__init__.py
abacusevents/__version__.py
abacusevents/abacusevents.py
abacusevents/pubsub.py
abacusevents/utils.py
abacusevents-0.0.8.dist-info/DESCRIPTION.rst
abacusevents-0.0.8.dist-info/METADATA
abacusevents-0.0.8.dist-info/RECORD
abacusevents-0.0.8.dist-info/WHEEL
abacusevents-0.0.8.dist-info/metadata.json
abacusevents-0.0.8.dist-info/top_level.txt
