Metadata-Version: 2.0
Name: abacusevents
Version: 0.0.8
Summary: Some common Python tools for sending events across Abacus services
Home-page: https://github.com/kairosfuture/abacusevents
Author: Awesome Soul
Author-email: info@a3j.se
License: MIT
Platform: UNKNOWN
Classifier: License :: OSI Approved :: MIT License
Classifier: Programming Language :: Python
Classifier: Programming Language :: Python :: 3
Classifier: Programming Language :: Python :: 3.4
Classifier: Programming Language :: Python :: 3.5
Classifier: Programming Language :: Python :: 3.6
Classifier: Programming Language :: Python :: Implementation :: CPython
Classifier: Programming Language :: Python :: Implementation :: PyPy
Requires-Python: >=3.4.6
